odoo/addons/commission_salesman/README.rst
odoo/addons/commission_salesman/__init__.py
odoo/addons/commission_salesman/__manifest__.py
odoo/addons/commission_salesman/i18n/ca.po
odoo/addons/commission_salesman/i18n/commission_salesman.pot
odoo/addons/commission_salesman/i18n/es.po
odoo/addons/commission_salesman/i18n/es_AR.po
odoo/addons/commission_salesman/i18n/it.po
odoo/addons/commission_salesman/i18n/sale_commission_salesman.pot
odoo/addons/commission_salesman/models/__init__.py
odoo/addons/commission_salesman/models/account_move.py
odoo/addons/commission_salesman/models/res_partner.py
odoo/addons/commission_salesman/models/sale_order.py
odoo/addons/commission_salesman/readme/CONFIGURE.rst
odoo/addons/commission_salesman/readme/CONTRIBUTORS.rst
odoo/addons/commission_salesman/readme/CREDITS.rst
odoo/addons/commission_salesman/readme/DESCRIPTION.rst
odoo/addons/commission_salesman/readme/ROADMAP.rst
odoo/addons/commission_salesman/readme/USAGE.rst
odoo/addons/commission_salesman/static/description/icon.png
odoo/addons/commission_salesman/static/description/icon.svg
odoo/addons/commission_salesman/static/description/index.html
odoo/addons/commission_salesman/tests/__init__.py
odoo/addons/commission_salesman/tests/test_sale_commission_salesman.py
odoo/addons/commission_salesman/views/res_partner_views.xml
odoo_addon_commission_salesman-15.0.1.0.0.3.dist-info/METADATA
odoo_addon_commission_salesman-15.0.1.0.0.3.dist-info/WHEEL
odoo_addon_commission_salesman-15.0.1.0.0.3.dist-info/top_level.txt
odoo_addon_commission_salesman-15.0.1.0.0.3.dist-info/RECORD
